README.rst
setup.py
tronapi/__init__.py
tronapi/constants.py
tronapi/contract.py
tronapi/exceptions.py
tronapi/main.py
tronapi/manager.py
tronapi/module.py
tronapi/transactionbuilder.py
tronapi/trx.py
tronapi.egg-info/PKG-INFO
tronapi.egg-info/SOURCES.txt
tronapi.egg-info/dependency_links.txt
tronapi.egg-info/not-zip-safe
tronapi.egg-info/requires.txt
tronapi.egg-info/top_level.txt
tronapi/common/__init__.py
tronapi/common/abi.py
tronapi/common/account.py
tronapi/common/blocks.py
tronapi/common/contracts.py
tronapi/common/datastructures.py
tronapi/common/datatypes.py
tronapi/common/encoding.py
tronapi/common/formatters.py
tronapi/common/normalizers.py
tronapi/common/threads.py
tronapi/common/transactions.py
tronapi/common/validation.py
tronapi/common/toolz/__init__.py
tronapi/providers/__init__.py
tronapi/providers/base.py
tronapi/providers/http.py