Metadata-Version: 2.1
Name: tronapi
Version: 3.1.4
Summary: A Python API for interacting with Tron (TRX)
Home-page: https://github.com/iexbase/tron-api-python
Author: Shamsudin Serderov
Author-email: steein.shamsudin@gmail.com
License: MIT License
Keywords: tron tron-api tron-api-python iexbase
Platform: UNKNOWN
Classifier: Development Status :: 3 - Alpha
Classifier: Intended Audience :: Developers
Classifier: License :: OSI Approved :: MIT License
Classifier: Natural Language :: English
Classifier: Programming Language :: Python :: 3
Classifier: Programming Language :: Python :: 3.6
Classifier: Programming Language :: Python :: 3.7
Requires-Python: >=3.6,<4
Provides-Extra: docs
Provides-Extra: tester
Provides-Extra: dev
